{"@class":"Animation","AnimationType":"object3D","OwnerLink":{"@class":"BindingLink","target":{"id":{"uuid":"CCE3F98B-D740-4BB0-A7F1-9F6A586CAAF9"},"type":0}},"id":{"uuid":"0573213E-0D96-412D-B81B-BB997E8402C2"},"is_imported":false,"tracks":[{"@class":"FloatBehaviorTrack","accessor":"FloatVariableAccessor","attribute":"posX","clips":[{"@class":"FloatBehaviorClip","beginTime":0,"behavior":{"@class":"FloatBezierBehavior","frames":[{"@class":"FloatBezierKeyFrame","formula":{"@class":"FloatExpressionFormula","expression":"getLocalPositionX('object__A5C4FB27_0249_4E94_B589_6C4DA30580A7')"},"order":"linear","point1":{"values":[0.0,0.0]},"point2":{"values":[0.0,0.0]},"time":0,"transition":false}]},"duration":0,"script":"FloatValueBehaviorClipScript"}],"script":"FloatBehaviorTrackScript"},{"@class":"FloatBehaviorTrack","accessor":"FloatVariableAccessor","attribute":"posY","clips":[{"@class":"FloatBehaviorClip","beginTime":0,"behavior":{"@class":"FloatBezierBehavior","frames":[{"@class":"FloatBezierKeyFrame","formula":{"@class":"FloatExpressionFormula","expression":"getLocalPositionY('object__2D8B0F7A_FBCD_415A_B09C_8337ABDF3B3E')"},"order":"linear","point1":{"values":[0.0,0.0]},"point2":{"values":[0.0,0.0]},"time":0,"transition":false}]},"duration":0,"script":"FloatValueBehaviorClipScript"}],"script":"FloatBehaviorTrackScript"},{"@class":"FloatBehaviorTrack","accessor":"FloatVariableAccessor","attribute":"posZ","clips":[{"@class":"FloatBehaviorClip","beginTime":0,"behavior":{"@class":"FloatBezierBehavior","frames":[{"@class":"FloatBezierKeyFrame","formula":{"@class":"FloatExpressionFormula","expression":"getLocalPositionZ('object__56B1C697_5EB5_4A5F_99BD_4E141A630812')"},"order":"linear","point1":{"values":[0.0,0.0]},"point2":{"values":[0.0,0.0]},"time":0,"transition":false}]},"duration":0,"script":"FloatValueBehaviorClipScript"}],"script":"FloatBehaviorTrackScript"}]}