{"@class":"Animation","AnimationType":"object3D","OwnerLink":{"@class":"BindingLink","target":{"id":{"uuid":"479671BE-AB48-4AE9-BE36-D112FEBDA003"},"type":0}},"id":{"uuid":"0B64E89F-219D-4314-9F6A-9E99F96DC7E3"},"is_imported":false,"tracks":[{"@class":"FloatBehaviorTrack","accessor":"RotationYBlendAccessor","clips":[{"@class":"FloatBehaviorClip","beginTime":0,"behavior":{"@class":"FloatBezierBehavior","frames":[{"@class":"FloatBezierKeyFrame","formula":{"@class":"FloatExpressionFormula","expression":"origin-object__64D5C953_2602_43C1_85CE_A48A75B720C8__Speed"},"order":"linear","point1":{"values":[0.0,0.0]},"point2":{"values":[0.0,0.0]},"time":0,"transition":true}]},"duration":0,"script":"FloatValueBehaviorClipScript"}],"script":"FloatBehaviorTrackScript"}]}