{"@class":"Animation","AnimationType":"object3D","OwnerLink":{"@class":"BindingLink","target":{"id":{"uuid":"E8617622-FB09-47AB-AD39-84B77BD63567"},"type":0}},"id":{"uuid":"127845CE-2154-4AD5-96E3-EC8B4FE798D4"},"is_imported":false,"tracks":[{"@class":"BoolBehaviorTrack","accessor":"Object3DEnabledBlendAccessor","clips":[{"@class":"BoolBehaviorClip","beginTime":0,"behavior":{"@class":"BoolDiscreteBehavior","frames":[{"@class":"BoolKeyFrame","formula":{"@class":"BoolExpressionFormula","expression":"true"},"time":0}]},"duration":0,"script":"BoolValueBehaviorClipScript"}],"script":"BoolBehaviorTrackScript"}]}