{"@class":"Animation","AnimationType":"object3D","OwnerLink":{"@class":"BindingLink","target":{"id":{"uuid":"49BACE9D-3612-4902-B013-33B4CC9D3C31"},"type":0}},"id":{"uuid":"1B5E8512-4832-4F38-8EC0-AD1F530A0212"},"is_imported":false,"tracks":[{"@class":"FloatBehaviorTrack","accessor":"PositionYBlendAccessor","clips":[{"@class":"FloatBehaviorClip","beginTime":0,"behavior":{"@class":"FloatBezierBehavior","frames":[{"@class":"FloatBezierKeyFrame","formula":{"@class":"FloatExpressionFormula","expression":"origin"},"order":"quadratic","point1":{"values":[0.41999998688697815,0.0]},"point2":{"values":[0.0,0.0]},"time":1200,"transition":true},{"@class":"FloatBezierKeyFrame","formula":{"@class":"FloatExpressionFormula","expression":"origin-20"},"order":"linear","point1":{"values":[0.0,0.0]},"point2":{"values":[0.0,0.0]},"time":2000,"transition":true}]},"duration":2000,"script":"FloatValueBehaviorClipScript"}],"script":"FloatBehaviorTrackScript"}]}