{"@class":"Animation","AnimationType":"object3D","OwnerLink":{"@class":"BindingLink","target":{"id":{"uuid":"DFC512C3-5463-4B04-9B2D-1313BA01FA9D"},"type":0}},"id":{"uuid":"226DBE8B-5BE1-4CC5-A2CE-A7CB0F191141"},"is_imported":false,"tracks":[{"@class":"BoolBehaviorTrack","accessor":"Object3DEnabledBlendAccessor","clips":[{"@class":"BoolBehaviorClip","beginTime":0,"behavior":{"@class":"BoolDiscreteBehavior","frames":[{"@class":"BoolKeyFrame","formula":{"@class":"BoolExpressionFormula","expression":"false"},"time":0}]},"duration":0,"script":"BoolValueBehaviorClipScript"}],"script":"BoolBehaviorTrackScript"}]}