{"@class":"Animation","AnimationType":"object3D","OwnerLink":{"@class":"BindingLink","target":{"id":{"uuid":"3DC90619-5037-436C-9FB9-6454D97EBB0B"},"type":0}},"id":{"uuid":"24CAAEB3-3727-44DF-8841-E38D27A05A5E"},"is_imported":false,"tracks":[{"@class":"BoolBehaviorTrack","accessor":"Object3DEnabledBlendAccessor","clips":[{"@class":"BoolBehaviorClip","beginTime":0,"behavior":{"@class":"BoolDiscreteBehavior","frames":[{"@class":"BoolKeyFrame","formula":{"@class":"BoolExpressionFormula","expression":"false"},"time":0}]},"duration":0,"script":"BoolValueBehaviorClipScript"}],"script":"BoolBehaviorTrackScript"}]}