{"@class":"Animation","AnimationType":"object3D","OwnerLink":{"@class":"BindingLink","target":{"id":{"uuid":"D83145FE-0494-4A8C-BD2C-59E14833D949"},"type":0}},"id":{"uuid":"2A01F3FA-D41B-46BE-86A6-ACFF5782EE57"},"is_imported":false,"tracks":[{"@class":"BoolBehaviorTrack","accessor":"Object3DEnabledBlendAccessor","clips":[{"@class":"BoolBehaviorClip","beginTime":0,"behavior":{"@class":"BoolDiscreteBehavior","frames":[{"@class":"BoolKeyFrame","formula":{"@class":"BoolExpressionFormula","expression":"true"},"time":300},{"@class":"BoolKeyFrame","formula":{"@class":"BoolExpressionFormula","expression":"false"},"time":0}]},"duration":300,"script":"BoolValueBehaviorClipScript"}],"script":"BoolBehaviorTrackScript"}]}