{"@class":"Animation","AnimationType":"object3D","OwnerLink":{"@class":"BindingLink","target":{"id":{"uuid":"18F47A82-6FCA-4E76-A886-6EAA4E1B6259"},"type":0}},"id":{"uuid":"2D085FD5-E3B6-47DB-9659-C8A0247E3599"},"is_imported":false,"tracks":[{"@class":"FloatBehaviorTrack","accessor":"RotationYBlendAccessor","clips":[{"@class":"FloatBehaviorClip","beginTime":0,"behavior":{"@class":"FloatBezierBehavior","frames":[{"@class":"FloatBezierKeyFrame","formula":{"@class":"FloatExpressionFormula","expression":"origin-object__99B6721F_6A4D_463E_AB57_58FE8D576E31__Speed"},"order":"linear","point1":{"values":[0.0,0.0]},"point2":{"values":[0.0,0.0]},"time":0,"transition":true}]},"duration":0,"script":"FloatValueBehaviorClipScript"}],"script":"FloatBehaviorTrackScript"}]}