{"@class":"Animation","AnimationType":"object3D","OwnerLink":{"@class":"BindingLink","target":{"id":{"uuid":"6E1CE925-EC4F-4E0C-AADA-44D8CB3E6679"},"type":0}},"id":{"uuid":"366BC75D-8BF3-4E69-96A9-063E002BCD60"},"is_imported":false,"tracks":[{"@class":"FloatBehaviorTrack","accessor":"PositionZBlendAccessor","clips":[{"@class":"FloatBehaviorClip","beginTime":0,"behavior":{"@class":"FloatBezierBehavior","frames":[{"@class":"FloatBezierKeyFrame","formula":{"@class":"FloatExpressionFormula","expression":"0"},"order":"linear","point1":{"values":[0.0,0.0]},"point2":{"values":[0.0,0.0]},"time":0,"transition":true},{"@class":"FloatBezierKeyFrame","formula":{"@class":"FloatExpressionFormula","expression":"1.5"},"order":"linear","point1":{"values":[0.0,0.0]},"point2":{"values":[0.0,0.0]},"time":100,"transition":true},{"@class":"FloatBezierKeyFrame","formula":{"@class":"FloatExpressionFormula","expression":"0"},"order":"linear","point1":{"values":[0.0,0.0]},"point2":{"values":[0.0,0.0]},"time":200,"transition":true}]},"duration":200,"script":"FloatValueBehaviorClipScript"}],"script":"FloatBehaviorTrackScript"}]}