{"@class":"Animation","AnimationType":"avar","OwnerLink":{"@class":"BindingLink","target":{"id":{"uuid":"F48278FA-0B86-463B-BF73-4899F2C968E3"},"type":0}},"id":{"uuid":"36AE0FDC-393A-4D99-9630-15C2EB499424"},"is_imported":false,"tracks":[{"@class":"FloatBehaviorTrack","accessor":"FloatVariableAccessor","attribute":"prevItemIndex","clips":[{"@class":"FloatBehaviorClip","beginTime":0,"behavior":{"@class":"FloatBezierBehavior","frames":[{"@class":"FloatBezierKeyFrame","formula":{"@class":"FloatExpressionFormula","expression":"if(isEmpty(object__69E61163_FC51_428B_B68A_8D2ECA3151A6__PrevItem)){0}else{getValueOfEntityVariable(object__98B0CC9C_17CB_4BE9_B93D_7027CB61E850__PrevItem,'runtimeIndex')}"},"order":"linear","point1":{"values":[0.0,0.0]},"point2":{"values":[0.0,0.0]},"time":0,"transition":false}]},"duration":0,"script":"FloatValueBehaviorClipScript"}],"script":"FloatBehaviorTrackScript"}]}