{"@class":"Animation","AnimationType":"object3D","OwnerLink":{"@class":"BindingLink","target":{"id":{"uuid":"FB56A06B-449A-4646-B02A-FDC99024ABF0"},"type":0}},"id":{"uuid":"4144B661-741E-4DDA-ADB3-BF8B77A92FE7"},"is_imported":false,"tracks":[{"@class":"FloatBehaviorTrack","accessor":"PositionXBlendAccessor","clips":[{"@class":"FloatBehaviorClip","beginTime":0,"behavior":{"@class":"FloatBezierBehavior","frames":[{"@class":"FloatBezierKeyFrame","formula":{"@class":"FloatExpressionFormula","expression":"origin-object__7C369B06_3B46_4BCC_BD4C_1EB3C26B03C2__speed"},"order":"linear","point1":{"values":[0.0,0.0]},"point2":{"values":[0.0,0.0]},"time":500,"transition":true},{"@class":"FloatBezierKeyFrame","formula":{"@class":"FloatExpressionFormula","expression":"origin"},"order":"linear","point1":{"values":[0.0,0.0]},"point2":{"values":[0.0,0.0]},"time":0,"transition":true}]},"duration":500,"script":"FloatValueBehaviorClipScript"}],"script":"FloatBehaviorTrackScript"}]}