{"@class":"Animation","AnimationType":"objStateStorage","OwnerLink":{"@class":"BindingLink","target":{"id":{"uuid":"2D8D9348-8E33-4CB9-9CC6-C99D22083C7E"},"type":4}},"id":{"uuid":"5F4D9C98-3D9D-4946-A1D9-335A35370878"},"is_imported":false,"name":"ObjectStateStorage","tracks":[{"@class":"ObjectStateStorageTrack","accessor":"ObjectStateStorageRestoreAccessor","clips":[{"@class":"ObjectStateStorageClip","beginTime":0,"behavior":{"@class":"ObjectStateStorageBehavior","frames":[{"@class":"BoolKeyFrame","formula":{"@class":"BoolExpressionFormula","expression":"false"},"time":0}]},"duration":0,"script":"ObjectStateStorageBehaviorClipScript"}],"script":"ObjectStateStorageTrackScript"}]}