{"@class":"Animation","AnimationType":"object3D","OwnerLink":{"@class":"BindingLink","target":{"id":{"uuid":"669C584F-DBA2-4C7C-850C-E35134CA2E45"},"type":0}},"id":{"uuid":"5F872C0F-6719-44BA-8731-D4E319D90D40"},"is_imported":false,"tracks":[{"@class":"FloatBehaviorTrack","accessor":"FloatVariableAccessor","attribute":"Points","clips":[{"@class":"FloatBehaviorClip","beginTime":0,"behavior":{"@class":"FloatBezierBehavior","frames":[{"@class":"FloatBezierKeyFrame","formula":{"@class":"FloatExpressionFormula","expression":"object__137E9C82_2503_491E_BBBE_4276E9E7F317__Points+Temp_Points"},"order":"linear","point1":{"values":[0.0,0.0]},"point2":{"values":[0.0,0.0]},"time":100,"transition":true}]},"duration":100,"script":"FloatValueBehaviorClipScript"}],"script":"FloatBehaviorTrackScript"},{"@class":"FloatBehaviorTrack","accessor":"FloatVariableAccessor","attribute":"Rank","clips":[{"@class":"FloatBehaviorClip","beginTime":0,"behavior":{"@class":"FloatBezierBehavior","frames":[{"@class":"FloatBezierKeyFrame","formula":{"@class":"FloatExpressionFormula","expression":"if(object__1CD36AF6_5269_40F0_8FDA_9D41AC912DA2__Points=10,1,if(object__C2B601C8_27B6_4345_91E9_4A1717D85E17__Points=6,2,If(object__E2F81251_6DAE_419B_BC22_5A3D62F86C17__Points=3,3,4)))"},"order":"linear","point1":{"values":[0.0,0.0]},"point2":{"values":[0.0,0.0]},"time":0,"transition":true}]},"duration":0,"script":"FloatValueBehaviorClipScript"}],"script":"FloatBehaviorTrackScript"},{"@class":"BoolBehaviorTrack","accessor":"BoolVariableAccessor","attribute":"Finished","clips":[{"@class":"BoolBehaviorClip","beginTime":0,"behavior":{"@class":"BoolDiscreteBehavior","frames":[{"@class":"BoolKeyFrame","formula":{"@class":"BoolExpressionFormula","expression":"true"},"time":200}]},"duration":200,"script":"BoolValueBehaviorClipScript"}],"script":"BoolBehaviorTrackScript"},{"@class":"BoolBehaviorTrack","accessor":"BoolVariableAccessor","attribute":"CONTROLLED","clips":[{"@class":"BoolBehaviorClip","beginTime":0,"behavior":{"@class":"BoolDiscreteBehavior","frames":[{"@class":"BoolKeyFrame","formula":{"@class":"BoolExpressionFormula","expression":"false"},"time":500}]},"duration":500,"script":"BoolValueBehaviorClipScript"}],"script":"BoolBehaviorTrackScript"}]}