{"@class":"Animation","AnimationType":"avar","OwnerLink":{"@class":"BindingLink","target":{"id":{"uuid":"1332C829-C71A-41CF-92EB-29FE04D7A3A2"},"type":0}},"id":{"uuid":"808833E8-95EB-47A4-84ED-901BC1F2B4D1"},"is_imported":false,"tracks":[{"@class":"FloatBehaviorTrack","accessor":"FloatVariableAccessor","attribute":"RR3","clips":[{"@class":"FloatBehaviorClip","beginTime":0,"behavior":{"@class":"FloatBezierBehavior","frames":[{"@class":"FloatBezierKeyFrame","formula":{"@class":"FloatExpressionFormula","expression":"if(RR1<3,if(rr1=1,2,1),if(rr1=3,4,3))"},"order":"linear","point1":{"values":[0.0,0.0]},"point2":{"values":[0.0,0.0]},"time":200,"transition":true}]},"duration":200,"script":"FloatValueBehaviorClipScript"}],"script":"FloatBehaviorTrackScript"}]}