{"@class":"Animation","AnimationType":"object3D","OwnerLink":{"@class":"BindingLink","target":{"id":{"uuid":"F570F5DA-688B-44C3-B978-BFA6F9F5BD30"},"type":0}},"id":{"uuid":"98E11AAE-CA78-4426-A3EC-E6539961E58D"},"is_imported":false,"tracks":[{"@class":"BoolBehaviorTrack","accessor":"Object3DEnabledBlendAccessor","clips":[{"@class":"BoolBehaviorClip","beginTime":0,"behavior":{"@class":"BoolDiscreteBehavior","frames":[{"@class":"BoolKeyFrame","formula":{"@class":"BoolExpressionFormula","expression":"true"},"time":300},{"@class":"BoolKeyFrame","formula":{"@class":"BoolExpressionFormula","expression":"false"},"time":0}]},"duration":300,"script":"BoolValueBehaviorClipScript"}],"script":"BoolBehaviorTrackScript"}]}