{"@class":"Animation","AnimationType":"object3D","OwnerLink":{"@class":"BindingLink","target":{"id":{"uuid":"022D7818-8A43-44A2-9262-1A34BFFC1222"},"type":0}},"id":{"uuid":"98E9398F-CBA0-42EC-9F24-F0C57212E249"},"is_imported":false,"tracks":[{"@class":"Vector3BehaviorTrack","accessor":"ColorBlendAccessor","clips":[{"@class":"Vector3BehaviorClip","beginTime":0,"behavior":{"@class":"Vector3BezierBehavior","frames":[{"@class":"Vector3BezierKeyFrame","formula":{"@class":"Vector3ExpressionFormula","expression":"var v[3]:={0.67982,0.502708,0.248707};return[v];"},"order":"linear","point1":{"values":[0.0,0.0]},"point2":{"values":[0.0,0.0]},"time":0,"transition":true}]},"duration":0,"script":"Vector3ValueBehaviorClipScript"}],"script":"Vector3BehaviorTrackScript"}]}