{"@class":"Animation","AnimationType":"object3D","OwnerLink":{"@class":"BindingLink","target":{"id":{"uuid":"9BCB3A50-C707-47CF-BF24-14B434D10D16"},"type":0}},"id":{"uuid":"BB10B113-57C9-4F2A-8471-ECBBD42E348C"},"is_imported":false,"tracks":[{"@class":"BoolBehaviorTrack","accessor":"Object3DEnabledBlendAccessor","clips":[{"@class":"BoolBehaviorClip","beginTime":0,"behavior":{"@class":"BoolDiscreteBehavior","frames":[{"@class":"BoolKeyFrame","formula":{"@class":"BoolExpressionFormula","expression":"true"},"time":300},{"@class":"BoolKeyFrame","formula":{"@class":"BoolExpressionFormula","expression":"false"},"time":0}]},"duration":300,"script":"BoolValueBehaviorClipScript"}],"script":"BoolBehaviorTrackScript"}]}