{"@class":"Animation","AnimationType":"object3D","OwnerLink":{"@class":"BindingLink","target":{"id":{"uuid":"20F40DEA-26D2-40C6-8ECA-651045E021C6"},"type":0}},"id":{"uuid":"D17BB0AC-848E-4C40-86EC-422535552068"},"is_imported":false,"tracks":[{"@class":"FloatBehaviorTrack","accessor":"PositionZBlendAccessor","clips":[{"@class":"FloatBehaviorClip","beginTime":0,"behavior":{"@class":"FloatBezierBehavior","frames":[{"@class":"FloatBezierKeyFrame","formula":{"@class":"FloatExpressionFormula","expression":"0"},"order":"linear","point1":{"values":[0.0,0.0]},"point2":{"values":[0.0,0.0]},"time":0,"transition":true},{"@class":"FloatBezierKeyFrame","formula":{"@class":"FloatExpressionFormula","expression":"1.5"},"order":"linear","point1":{"values":[0.0,0.0]},"point2":{"values":[0.0,0.0]},"time":100,"transition":true},{"@class":"FloatBezierKeyFrame","formula":{"@class":"FloatExpressionFormula","expression":"0"},"order":"linear","point1":{"values":[0.0,0.0]},"point2":{"values":[0.0,0.0]},"time":200,"transition":true}]},"duration":200,"script":"FloatValueBehaviorClipScript"}],"script":"FloatBehaviorTrackScript"}]}