{"@class":"Animation","AnimationType":"object3D","OwnerLink":{"@class":"BindingLink","target":{"id":{"uuid":"BA5BE6AF-0A57-4FDA-867E-B7C93D832A0E"},"type":0}},"id":{"uuid":"D6839EB0-BCF3-4854-8206-4DD9E6624141"},"is_imported":false,"tracks":[{"@class":"Vector3BehaviorTrack","accessor":"ColorBlendAccessor","clips":[{"@class":"Vector3BehaviorClip","beginTime":0,"behavior":{"@class":"Vector3BezierBehavior","frames":[{"@class":"Vector3BezierKeyFrame","formula":{"@class":"Vector3ExpressionFormula","expression":"var v[3]:={0.521279,0.307118,0};return[v];"},"order":"linear","point1":{"values":[0.0,0.0]},"point2":{"values":[0.0,0.0]},"time":0,"transition":true}]},"duration":0,"script":"Vector3ValueBehaviorClipScript"}],"script":"Vector3BehaviorTrackScript"}]}