{"@class":"Animation","AnimationType":"object3D","OwnerLink":{"@class":"BindingLink","target":{"id":{"uuid":"757B1B32-3DCF-4A76-B629-7F27777D7CBA"},"type":0}},"id":{"uuid":"E0AF40C8-8246-44D9-896B-4502BBB13EF5"},"is_imported":false,"tracks":[{"@class":"BoolBehaviorTrack","accessor":"BoolVariableAccessor","attribute":"Reset","clips":[{"@class":"BoolBehaviorClip","beginTime":0,"behavior":{"@class":"BoolDiscreteBehavior","frames":[{"@class":"BoolKeyFrame","formula":{"@class":"BoolExpressionFormula","expression":"true"},"time":3000},{"@class":"BoolKeyFrame","formula":{"@class":"BoolExpressionFormula","expression":"false"},"time":3100}]},"duration":3100,"script":"BoolValueBehaviorClipScript"}],"script":"BoolBehaviorTrackScript"}]}