{"@class":"Animation","AnimationType":"timeline","OwnerLink":{"@class":"BindingLink","target":{"type":0}},"id":{"uuid":"EA61479D-4176-4E1E-BACB-CAC25522D54A"},"is_imported":false,"tracks":[{"@class":"TimeLineTrack","accessor":"TimeLineAccessor","clips":[{"@class":"TimeLineClip","beginTime":0,"behavior":{"@class":"TimeLineBehavior","speed":1.0,"weights":{}},"bindinglink":{"@class":"BindingLink","target":{"id":{"uuid":"72CCEAEA-34BD-4DEF-9628-8550FF795A58"},"type":0}},"color":{"values":[0.0,0.0,0.0]},"duration":533,"script":"TimeLineClipScript"}],"script":"TimeLineTrackScript"}]}