{"@class":"Animation","AnimationType":"object3D","OwnerLink":{"@class":"BindingLink","target":{"id":{"uuid":"E8A8865C-C700-4BA4-BEA0-E5EDFAC8B889"},"type":0}},"id":{"uuid":"ED5938EA-4C3F-4E39-935B-65B55F0FB738"},"is_imported":false,"tracks":[{"@class":"BoolBehaviorTrack","accessor":"Object3DEnabledBlendAccessor","clips":[{"@class":"BoolBehaviorClip","beginTime":0,"behavior":{"@class":"BoolDiscreteBehavior","frames":[{"@class":"BoolKeyFrame","formula":{"@class":"BoolExpressionFormula","expression":"true"},"time":300},{"@class":"BoolKeyFrame","formula":{"@class":"BoolExpressionFormula","expression":"false"},"time":0}]},"duration":300,"script":"BoolValueBehaviorClipScript"}],"script":"BoolBehaviorTrackScript"}]}