{"@class":"Animation","AnimationType":"object3D","OwnerLink":{"@class":"BindingLink","target":{"id":{"uuid":"341C3EE4-59F9-4F0D-923B-73E838D633A7"},"type":0}},"id":{"uuid":"FAC1405D-8C34-4ED3-BBE7-D338F1B82484"},"is_imported":false,"tracks":[{"@class":"BoolBehaviorTrack","accessor":"Object3DEnabledBlendAccessor","clips":[{"@class":"BoolBehaviorClip","beginTime":0,"behavior":{"@class":"BoolDiscreteBehavior","frames":[{"@class":"BoolKeyFrame","formula":{"@class":"BoolExpressionFormula","expression":"true"},"time":300},{"@class":"BoolKeyFrame","formula":{"@class":"BoolExpressionFormula","expression":"false"},"time":0}]},"duration":300,"script":"BoolValueBehaviorClipScript"}],"script":"BoolBehaviorTrackScript"}]}