{"@class":"Animation","AnimationType":"object3D","OwnerLink":{"@class":"BindingLink","target":{"id":{"uuid":"712977B5-8A76-460F-8669-FD82D0843629"},"type":0}},"id":{"uuid":"FFA67EB8-E4A7-45B1-B7E0-8BEB69929B6E"},"is_imported":false,"tracks":[{"@class":"BoolBehaviorTrack","accessor":"Object3DEnabledBlendAccessor","clips":[{"@class":"BoolBehaviorClip","beginTime":0,"behavior":{"@class":"BoolDiscreteBehavior","frames":[{"@class":"BoolKeyFrame","formula":{"@class":"BoolExpressionFormula","expression":"true"},"time":0}]},"duration":0,"script":"BoolValueBehaviorClipScript"}],"script":"BoolBehaviorTrackScript"}]}