{"@class":"PhysicsBody","bounciness":50.0,"ccdMotionThreshold":0.0,"ccdSweptSphereRadius":0.0,"friction":0.0,"gravity":{"values":[0.0,0.0,0.0]},"id":{"uuid":"085B74E7-A683-40C4-88EF-FE42F7380D93"},"initAngularVelocity":{"values":[0.0,0.0,0.0]},"initLinearVelocity":{"values":[0.0,0.0,0.0]},"lockPositionX":false,"lockPositionY":false,"lockPositionZ":false,"lockRotationX":false,"lockRotationY":false,"lockRotationZ":false,"mass":0.0010000000474974513,"physBodyType":"kinematic","physSurfaceType":"defaultSurfaceType","useCCD":false,"useCustomGravity":false,"useLocalInitialVelocities":false}